glucostats/__init__.py
glucostats/extract_statistics.py
glucostats/main.py
glucostats/stats/__init__.py
glucostats/stats/control_stats.py
glucostats/stats/descriptive_stats.py
glucostats/stats/observations_stats.py
glucostats/stats/risks_stats.py
glucostats/stats/time_stats.py
glucostats/stats/variability_stats.py
glucostats/utils/__init__.py
glucostats/utils/batching.py
glucostats/utils/constants.py
glucostats/utils/format_verification.py
glucostats/utils/split_in_days.py
glucostats/utils/transform_units.py
glucostats/utils/windowing.py
glucostats/visualization/__init__.py
glucostats/visualization/heatmaps.py
glucostats/visualization/signal_visualization.py
glucostats-1.0.0.dist-info/licenses/LICENSE.txt
glucostats-1.0.0.dist-info/METADATA
glucostats-1.0.0.dist-info/WHEEL
glucostats-1.0.0.dist-info/top_level.txt
glucostats-1.0.0.dist-info/RECORD
