Metadata-Version: 2.4
Name: glucostats
Version: 1.0.0
Summary: GlucoStats, an open-source, multi-processing Python package designed for the efficient computation and visualization of a comprehensive set of glucose metrics derived from continuous glucose monitoring (CGM) data
Author-email: David Chushig-Muzo <david.chushig@urjc.es>, Pablo Peiro-Corbacho <pablo.peiro@urjc.es>, Francisco J Lara-Abelenda <francisco.lara@urjc.es>
License: BSD 2-Clause License
Project-URL: Documentation, https://glucostats.readthedocs.io/en/latest/
Project-URL: Repository, https://github.com/ai4healthurjc/GlucoStats
Keywords: continuous glucose monitoring,glucose,feature extraction,Python,glucose data analysis,sliding time window,Parallelization,Glucose visualization
Classifier: Intended Audience :: Science/Research
Classifier: Topic :: Scientific/Engineering
Classifier: Programming Language :: Python :: 3
Requires-Python: >=3.10.12
License-File: LICENSE.txt
Requires-Dist: numpy==2.2.3
Requires-Dist: matplotlib>=3.8.0
Requires-Dist: pandas==2.2.3
Requires-Dist: neurokit2==0.2.10
Requires-Dist: seaborn==0.13.2
Requires-Dist: tqdm==4.67.1
Requires-Dist: scipy==1.15.2
Requires-Dist: colorlog==4.6.0
Dynamic: license-file
